query_quiver/__init__.py
query_quiver/chrome_history.py
query_quiver/cli.py
query_quiver/downloader.py
query_quiver/generator.py
query_quiver/logger.py
query_quiver/prompt.py
query_quiver/types.py
query_quiver-0.0.4.dist-info/LICENSE
query_quiver-0.0.4.dist-info/METADATA
query_quiver-0.0.4.dist-info/WHEEL
query_quiver-0.0.4.dist-info/entry_points.txt
query_quiver-0.0.4.dist-info/RECORD
