Metadata-Version: 2.1
Name: query_quiver
Version: 0.0.4
Summary: Support brainstorming for technical blog using your Google Chrome history.
Home-page: https://github.com/marutaku
Author: marutaku
Author-email: satouredstone@gmail.com
Requires-Python: >=3.11,<4.0
Classifier: Programming Language :: Python :: 3
Classifier: Programming Language :: Python :: 3.11
Classifier: Programming Language :: Python :: 3.12
Requires-Dist: beautifulsoup4 (>=4.12.2,<5.0.0)
Requires-Dist: fire (>=0.5.0,<0.6.0)
Requires-Dist: openai (>=1.6.1,<2.0.0)
Requires-Dist: requests (>=2.31.0,<3.0.0)
Requires-Dist: tiktoken (>=0.5.2,<0.6.0)
Project-URL: Repository, https://github.com/marutaku/QueryQuiver
